{
    "version": "7.3.5",
    "homepage": "https://github.com/mvdctop/Movie_Data_Capture",
    "description": "Movie Metadata Crawler | Scraper",
    "license": "GPL-3.0-only",
    "url": "https://github.com/mvdctop/Movie_Data_Capture/releases/download/7.3.5/MDC-7.3.5-Windows-x86_64.zip",
    "hash": "1d0f994c8f632b603c5b392b941a5f0a1eb16a6e34f2bc4fa4f976753842bfc9",
    "shortcuts": [
        [
            "MDC.exe",
            "Movie Data Capture"
        ]
    ],
    "pre_install": [
        "$ini = \"config.ini\"",
        "if (!(Test-Path \"$persist_dir\\$ini\")) {",
        "   New-Item -Path \"$dir\\$ini\" -ItemType File",
        "}"
    ],
    "persist": "config.ini",
    "checkver": "github",
    "autoupdate": {
        "url": "https://github.com/mvdctop/Movie_Data_Capture/releases/download/$version/MDC-$version-Windows-x86_64.zip"
    }
}
